Workbook

Sheet README Model Map
A1: README / Assumptions / Model Map
A3: Item | B3: Current treatment
A4: Model version/date | B4: 2026-05-27 financial diligence draft.
A5: Owner | B5: Founder-prepared; pending CFO/counsel review.
A6: Intended use | B6: Controlled diligence and investor follow-up. Not a public/front-of-room handout by default.
A7: Not advice | B7: Not legal, tax, accounting, securities, or valuation advice.
A8: Core raise assumption | B8: $5M target pre-seed; staged close structure and final terms counsel/CFO pending.
A9: Runway assumption | B9: Target plan models roughly 18-24 months: $1.85M planned spend plus $150K reserve.
A10: Revenue assumption | B10: No revenue forecast. Reservation pricing is a qualification/scoping signal only.
A11: Investor-facing sheets | B11: Use of Funds; Runway & Burn; Dilution Sensitivity; Milestone Gates; Market Context; Caveats.
A12: Internal/control sheets | B12: 18-Month Cash Plan; Evaluation Pricing; Evaluation SOW Economics; Cap Table Draft; Unmodeled / CFO Needs.
A13: Do not change without review | B13: Raise scenarios, SAFE sensitivity, source-backed market figures, and claim guardrails.
A14: Source register | B14: See ATOMiK_Financial_Source_Register and Market Context source URL column.
A15: Open diligence gaps | B15: CFO/counsel terms, option pool, taxes/benefits, insurance, legal close costs, vendor quotes, and first signed SOW.
A18: Use this workbook as a controlled milestone model. Do not distribute as final CFO-approved terms.
A19: Revenue Scenario | B19: Founder-prepared planning ranges for proof reviews, SOWs, design partners, and licensing path. Not a forecast.

Sheet Use of Funds
A1: ATOMiK - Pre-Seed Use of Funds (Formula-Backed)
A2: Category | B2: Staged $3M | C2: Target $5M | D2: Expanded $7.5M | E2: Target % | F2: Proof Gate / Purpose
A3: Engineering & Demo | B3: 900000 | C3: 1500000 | D3: 2250000 | E3: =C3/$C$9 | F3: Repeatable investor/design-partner proof system.
A4: Customer Proof | B4: 600000 | C4: 1000000 | D4: 1500000 | E4: =C4/$C$9 | F4: First measured workload artifact with correctness preserved.
A5: IP / Legal | B5: 450000 | C5: 750000 | D5: 1125000 | E5: =C5/$C$9 | F5: Counsel-reviewed IP packet and patent-conversion plan.
A6: ASIC Feasibility | B6: 450000 | C6: 750000 | D6: 1125000 | E6: =C6/$C$9 | F6: Go/no-go feasibility report; quote-backed path; no tape-out funding.
A7: Finance / GTM / Ops | B7: 360000 | C7: 600000 | D7: 900000 | E7: =C7/$C$9 | F7: CFO support, investor reporting, design-partner outreach, entity/admin readiness.
A8: Reserve | B8: 240000 | C8: 400000 | D8: 600000 | E8: =C8/$C$9 | F8: Runway buffer and proof-cost reserve; do not convert expanded capacity into overbuild.
A9: TOTAL | B9: =SUM(B3:B8) | C9: =SUM(C3:C8) | D9: =SUM(D3:D8) | E9: =SUM(E3:E8) | F9: Funds proof, IP, feasibility, operations. Does not fund tape-out.
A11: CFO diligence note: amounts are milestone-planning allocations. Vendor quotes, hiring plan, tax/accounting treatment, and legal close mechanics still require approval.

Sheet Runway & Burn
A1: Runway And Burn Sensitivity
A2: Scenario | B2: Raise | C2: Reserve | D2: Spendable Cash | E2: Planning Months | F2: Gross $/Month | G2: Ex-Reserve $/Month | H2: Notes
A3: Staged | B3: 3000000 | C3: 250000 | D3: =B3-C3 | E3: 18 | F3: =B3/E3 | G3: =D3/E3 | H3: Staged close path: counsel/CFO pending; keeps proof, IP, and first customer workload path moving.
A4: Target | B4: 5000000 | C4: 400000 | D4: =B4-C4 | E4: 24 | F4: =B4/E4 | G4: =D4/E4 | H4: Aggie-facing target ask: workload proof, IP packet, ASIC feasibility, and first technical capacity.
A5: Expanded | B5: 7500000 | C5: 600000 | D5: =B5-C5 | E5: 24 | F5: =B5/E5 | G5: =D5/E5 | H5: Expanded capacity; not tape-out. Faster hiring and broader evaluation support.
A7: Target-plan monthly budget by category. These are average equivalents, not a monthly hiring commitment; spend should be staged by milestone.
A8: Category | B8: Target Allocation | C8: Months | D8: Avg $/Month | E8: Gate
A9: Engineering & Demo | B9: 1500000 | C9: ='Runway & Burn'!$E$4 | D9: =B9/C9 | E9: Repeatable investor/design-partner proof system.
A10: Customer Proof | B10: 1000000 | C10: ='Runway & Burn'!$E$4 | D10: =B10/C10 | E10: First measured workload artifact with correctness preserved.
A11: IP / Legal | B11: 750000 | C11: ='Runway & Burn'!$E$4 | D11: =B11/C11 | E11: Counsel-reviewed IP packet and patent-conversion plan.
A12: ASIC Feasibility | B12: 750000 | C12: ='Runway & Burn'!$E$4 | D12: =B12/C12 | E12: Go/no-go feasibility report; quote-backed path; no tape-out funding.
A13: Finance / GTM / Ops | B13: 600000 | C13: ='Runway & Burn'!$E$4 | D13: =B13/C13 | E13: CFO support, investor reporting, design-partner outreach, entity/admin readiness.
A14: Reserve | B14: 400000 | C14: ='Runway & Burn'!$E$4 | D14: =B14/C14 | E14: Runway buffer; do not convert stretch into overbuild.
A16: Formula check: target allocation total | B16: =SUM(B9:B14) | D16: =SUM(D9:D14) | E16: Monthly total should equal target gross/month.

Sheet 18-Month Cash Plan
A1: 24-Month Target Cash Plan - $5M Raise
A2: Target-plan monthly budget. Values are planning allocations, not approved hiring commitments. Spend should be staged behind proof gates and vendor quotes.
A4: Line Item | B4: M1 | C4: M2 | D4: M3 | E4: M4 | F4: M5 | G4: M6 | H4: M7 | I4: M8 | J4: M9 | K4: M10 | L4: M11 | M4: M12 | N4: M13 | O4: M14 | P4: M15 | Q4: M16 | R4: M17 | S4: M18 | T4: Total | U4: Notes
A5: Engineering capacity / contractors | B5: 20000 | C5: 20000 | D5: 30000 | E5: 30000 | F5: 30000 | G5: 30000 | H5: 30000 | I5: 30000 | J5: 30000 | K5: 30000 | L5: 30000 | M5: 30000 | N5: 30000 | O5: 30000 | P5: 30000 | Q5: 30000 | R5: 30000 | S5: 30000 | T5: =SUM(B5:S5) | U5: FPGA/ASIC and workload-validation capacity; hire timing staged by close.
A6: Demo hardware, tools, packaging | B6: 20000 | C6: 20000 | D6: 10000 | E6: 10000 | F6: 10000 | G6: 10000 | H6: 0 | I6: 0 | J6: 0 | K6: 0 | L6: 0 | M6: 0 | N6: 0 | O6: 0 | P6: 0 | Q6: 0 | R6: 0 | S6: 0 | T6: =SUM(B6:S6) | U6: Boards, test equipment, software/tooling, investor-demo reliability.
A7: Customer workload proof | B7: 5000 | C7: 5000 | D7: 20000 | E7: 20000 | F7: 20000 | G7: 20000 | H7: 30000 | I7: 30000 | J7: 30000 | K7: 30000 | L7: 30000 | M7: 30000 | N7: 21666.667 | O7: 21666.667 | P7: 21666.667 | Q7: 21666.667 | R7: 21666.667 | S7: 21666.667 | T7: =SUM(B7:S7) | U7: Evaluation harnesses, traces, baseline work, proof artifacts.
A8: IP / legal | B8: 30000 | C8: 30000 | D8: 30000 | E8: 30000 | F8: 25000 | G8: 25000 | H8: 25000 | I8: 25000 | J8: 20000 | K8: 20000 | L8: 20000 | M8: 20000 | N8: 0 | O8: 0 | P8: 0 | Q8: 0 | R8: 0 | S8: 0 | T8: =SUM(B8:S8) | U8: Patent conversion, prior art, entity/IP cleanup, diligence packet.
A9: ASIC feasibility | B9: 5000 | C9: 5000 | D9: 5000 | E9: 10000 | F9: 10000 | G9: 10000 | H9: 30000 | I9: 30000 | J9: 30000 | K9: 30000 | L9: 30000 | M9: 30000 | N9: 12500 | O9: 12500 | P9: 12500 | Q9: 12500 | R9: 12500 | S9: 12500 | T9: =SUM(B9:S9) | U9: Mentor, feasibility scoping, external review; no tape-out.
A10: Finance / GTM / ops | B10: 13888.889 | C10: 13888.889 | D10: 13888.889 | E10: 13888.889 | F10: 13888.889 | G10: 13888.889 | H10: 13888.889 | I10: 13888.889 | J10: 13888.889 | K10: 13888.889 | L10: 13888.889 | M10: 13888.889 | N10: 13888.889 | O10: 13888.889 | P10: 13888.889 | Q10: 13888.889 | R10: 13888.889 | S10: 13888.889 | T10: =SUM(B10:S10) | U10: Fractional CFO/accounting, investor reporting, outreach, insurance/admin.
A12: Monthly planned spend | B12: =SUM(B5:B10) | C12: =SUM(C5:C10) | D12: =SUM(D5:D10) | E12: =SUM(E5:E10) | F12: =SUM(F5:F10) | G12: =SUM(G5:G10) | H12: =SUM(H5:H10) | I12: =SUM(I5:I10) | ... S12: =SUM(S5:S10) | T12: =SUM(B12:S12) | U12: Should equal $1.85M spendable target cash, excluding $150K reserve.
A13: Cumulative spend | B13: =SUM($B$12:B$12) | C13: =SUM($B$12:C$12) | D13: =SUM($B$12:D$12) | E13: =SUM($B$12:E$12) | F13: =SUM($B$12:F$12) | G13: =SUM($B$12:G$12) | H13: =SUM($B$12:H$12) | I13: =SUM($B$12:I$12) | ... S13: =SUM($B$12:S$12) | T13: =S13 | U13: Tracks spend against target spendable cash.
A14: Remaining spendable cash | B14: =IF(ABS(1850000-B13)<1,0,ROUND(1850000-B13,0)) | C14: =IF(ABS(1850000-C13)<1,0,ROUND(1850000-C13,0)) | D14: =IF(ABS(1850000-D13)<1,0,ROUND(1850000-D13,0)) | E14: =IF(ABS(1850000-E13)<1,0,ROUND(1850000-E13,0)) | F14: =IF(ABS(1850000-F13)<1,0,ROUND(1850000-F13,0)) | G14: =IF(ABS(1850000-G13)<1,0,ROUND(1850000-G13,0)) | H14: =IF(ABS(1850000-H13)<1,0,ROUND(1850000-H13,0)) | I14: =IF(ABS(1850000-I13)<1,0,ROUND(1850000-I13,0)) | ... S14: =IF(ABS(1850000-S13)<1,0,ROUND(1850000-S13,0)) | T14: =S14 | U14: Target raise minus reserve is $1.85M.
A15: Reserve held | B15: 150000 | C15: 150000 | D15: 150000 | E15: 150000 | F15: 150000 | G15: 150000 | H15: 150000 | I15: 150000 | J15: 150000 | K15: 150000 | L15: 150000 | M15: 150000 | N15: 150000 | O15: 150000 | P15: 150000 | Q15: 150000 | R15: 150000 | S15: 150000 | T15: 150000 | U15: Held as buffer; not included in planned spend.
A17: Cash-plan check: B12:S12 totals should equal $1.85M and row 15 should preserve the $150K target reserve. Add taxes, benefits, and exact vendor quotes once CFO/accounting has current assumptions.

Sheet Evaluation Pricing
A1: Evaluation Pricing And Revenue Signals - Planning Only
A2: This sheet is not a revenue forecast. Reservation prices qualify interest and may be credited toward larger scoped work; larger evaluations require written SOWs.
A4: Offer | B4: Public / Planning Price | C4: External Wording | D4: Financial Treatment | E4: Caveat
A5: Proof Review Reservation | B5: 750 | C5: One-time reservation for proof/workload review. | D5: Small qualification payment; not material revenue. | E5: Does not create commercial license or prove customer demand by itself.
A6: Technical Evaluation Reservation | B6: 2500 | C6: One-time reservation for evaluation scoping. | D6: Small qualification payment; may convert into scoped SOW. | E6: Final deliverables and terms confirmed separately.
A7: Scoped Design Partner Evaluation | B7: Request-based | C7: Written scope around workload, baseline, metric, deliverables. | D7: Potential first material customer-funded proof path. | E7: No forecast until signed SOW.
A8: Licensing / IP Diligence | B8: Request-based | C8: Partner-specific diligence path. | D8: Future/mid-term revenue candidate. | E8: Requires workload proof, IP packet, and integration path.
A9: Commercial Licensing / Embedded IP | B9: Future | C9: Not a pre-seed revenue forecast. | D9: Strategic upside path. | E9: Do not quote license pricing before customer/partner evidence.
A12: Illustrative reservation cash only - not a forecast and not a valuation input.
A13: Input | B13: Conservative | C13: Base | D13: Upside | E13: Notes
A14: Proof review reservations | B14: 0 | C14: 2 | D14: 5 | E14: Uses current public $750 reservation.
A15: Technical eval reservations | B15: 0 | C15: 1 | D15: 3 | E15: Uses current public $2,500 reservation.
A16: Reservation cash | B16: =B14*750+B15*2500 | C16: =C14*750+C15*2500 | D16: =D14*750+D15*2500 | E16: Qualification signal only; serious revenue requires SOW.
A17: Scoped SOW revenue | B17: TBD | C17: TBD | D17: TBD | E17: Do not forecast until a written scope exists.

Sheet Evaluation SOW Economics
A1: Evaluation SOW Economics - Planning Only
A2: Planning template only. Do not forecast revenue until a signed SOW defines price, scope, deliverables, ownership, and acceptance criteria.
A4: Workstream | B4: What it covers | C4: Commercial treatment | D4: Diligence caveat
A5: Workload intake | B5: Representative workload, baseline, painful constraint, and target environment. | C5: TBD / scoped quote only. | D5: Not forecast until customer supplies scope and signs terms.
A6: Baseline mapping | B6: Current implementation, state path, trace/logs, and agreed measurement method. | C6: May be included in scoped evaluation fee. | D6: Requires customer artifacts; no customer-value claim without baseline.
A7: Success metric definition | B7: One primary metric and decision threshold. | C7: Included in evaluation scope. | D7: Metric must preserve correctness and map to buyer pain.
A8: Test harness / artifacts | B8: Trace replay, baseline vs ATOMiK path, raw logs, proof card, and claims entry. | C8: Potential material customer-funded proof path. | D8: No public claim unless correctness passes and artifacts are reproducible.
A9: Readout | B9: Workload map, baseline comparison, evidence map, fit/no-fit recommendation. | C9: Deliverable of technical evaluation. | D9: Fit/no-fit is a valid outcome; do not promise positive results.
A10: Partner-funded proof work | B10: Optional deeper integration after proof review. | C10: Request-based SOW. | D10: Requires counsel review for IP, confidentiality, and ownership.
A11: Accounting treatment | B11: Revenue recognition and booking treatment. | C11: Pending CFO/accounting. | D11: Do not model until signed SOW and accounting review.

Sheet Revenue Scenario
A1: ATOMiK Founder-Prepared Revenue Scenario
A2: Planning scenario for investor discussion. Not a forecast; revenue depends on signed SOWs, measured workload proof, and partner diligence.
A4: Window | B4: Commercial motion | C4: Planning revenue range | D4: Required evidence gate
A5: 0-6 months | B5: Qualified proof reviews / technical evaluations | C5: $0-$150K | D5: Customer workload candidate, baseline, and success metric defined
A6: 6-12 months | B6: 2-3 paid evaluation or design-partner SOWs | C6: $250K-$750K | D6: Signed SOWs, correctness-preserving test plan, measured readout artifact
A7: 12-24 months | B7: 1-2 licensing or design-partner conversions if proof holds | C7: $1M-$3M potential contracted value | D7: Measured workload proof, IP diligence, and partner decision record
A8: 24-36 months | B8: 1-3 IP/license relationships if proof and economics hold | C8: $3M-$8M annualized potential | D8: Counsel-reviewed IP packet, feasibility review, and customer evidence
A11: Planning assumptions
A12: Planning status | B12: Founder-prepared scenario, not forecast. Pending CFO/counsel review.
A13: Proof review / technical evaluation | B13: Potential $25K-$75K scoped work when paid and appropriate.
A14: Design partner validation | B14: Potential $100K-$250K scoped validation/integration when paid and appropriate.
A15: Licensing model | B15: Upfront licensing plus per-unit royalty only if measured proof and partner diligence support it.
A16: Do not claim | B16: Booked revenue, committed pipeline, guaranteed ROI, or customer savings.

Sheet Milestone Gates
A1: 18-Month Milestone Gates
A2: Window | B2: Milestone | C2: Budget Owner | D2: Evidence Gate | E2: Investor Readout
A3: 0-30 days | B3: Lock financing structure, counsel plan, design-partner target list. | C3: Finance / Legal | D3: CFO/counsel reviewed plan. | E3: Terms are ready to circulate; no improvised cap.
A4: 30-60 days | B4: Harden Zynq demo into repeatable package. | C4: Engineering | D4: Demo checklist and current artifact bundle. | E4: Prototype proof is lower-friction and repeatable.
A5: 60-90 days | B5: Define first customer workload and baseline plan. | C5: Customer Proof | D5: Evaluation SOW and one success metric. | E5: Qualified workload exists or no-fit is documented.
A6: 90-180 days | B6: Produce first measured workload artifact. | C6: Customer Proof / Engineering | D6: Correctness-preserving workload result. | E6: Evidence-backed customer-value claim for one workload.
A7: 6-9 months | B7: Convert artifact into paid evaluation, LOI, or no-fit decision. | C7: GTM / Customer Proof | D7: Customer decision record. | E7: Early commercial signal or disciplined learning.
A8: 9-12 months | B8: Complete ASIC feasibility scope and IP diligence packet. | C8: ASIC / Legal | D8: Mentor-reviewed feasibility and counsel-reviewed IP memo. | E8: Silicon path is scoped without tape-out spend.
A9: 12-18-24 months | B9: Prepare next financing or strategic partner process. | C9: Finance / GTM | D9: Measured proof, partner pipeline, IP packet. | E9: Next-round or strategic diligence package.

Sheet Dilution Sensitivity
A1: Post-Money SAFE Dilution Sensitivity - Illustrative Only
A2: Not a valuation recommendation. Shows ownership sold under illustrative SAFE cap math before option-pool changes, prior instruments, side letters, or priced-round mechanics.
A4: Post-Money Cap | B4: $3M Staged | C4: $5M Target | D4: $7.5M Expanded | E4: Founder Before Pool (Target) | F4: Use In Room
A5: 8000000 | B5: =3000000/A5 | C5: =5000000/A5 | D5: =7500000/A5 | E5: =1-C5 | F5: CFO/counsel must set actual cap; do not offer in room.
A6: 10000000 | B6: =3000000/A6 | C6: =5000000/A6 | D6: =7500000/A6 | E6: =1-C6 | F6: CFO/counsel must set actual cap; do not offer in room.
A7: 12000000 | B7: =3000000/A7 | C7: =5000000/A7 | D7: =7500000/A7 | E7: =1-C7 | F7: CFO/counsel must set actual cap; do not offer in room.
A8: 15000000 | B8: =3000000/A8 | C8: =5000000/A8 | D8: =7500000/A8 | E8: =1-C8 | F8: CFO/counsel must set actual cap; do not offer in room.
A9: 18000000 | B9: =3000000/A9 | C9: =5000000/A9 | D9: =7500000/A9 | E9: =1-C9 | F9: CFO/counsel must set actual cap; do not offer in room.
A12: Rule of thumb: at a $25M post-money cap, a $5M SAFE implies 20.0% SAFE ownership before option-pool and later-round effects. This is sensitivity math, not a cap recommendation.

Sheet Market Context
A1: Market Context - Source-Backed Reference Data
A2: Metric | B2: Current | C2: Projected / Context | D2: Source / Use | E2: Primary source URL
A3: Global data-center energy | B3: 415 TWh (2024) | C3: ~945 TWh by 2030 | D3: IEA Energy and AI. Why-now context only. | E3: https://www.iea.org/reports/energy-and-ai/energy-demand-from-ai
A4: U.S. data-center energy | B4: 176 TWh (2023) | C4: 325-580 TWh (2028) | D4: LBNL 2024 U.S. Data Center Report. | E4: https://eta-publications.lbl.gov/sites/default/files/2024-12/lbnl-2024-united-states-data-center-energy-usage-report_1.pdf
A5: U.S. data-center cooling water | B5: 66B liters (2023) | C5: 60-124B liters hyperscale direct use (2028) | D5: LBNL. Water savings require site-specific proof. | E5: https://eta-publications.lbl.gov/sites/default/files/2024-12/lbnl-2024-united-states-data-center-energy-usage-report_1.pdf
A6: Global semiconductor sales | B6: $791.7B (2025) | C6: Q1 2026 sales $298.5B | D6: SIA. Backdrop only; not ATOMiK TAM. | E6: https://www.semiconductors.org/global-annual-semiconductor-sales-increase-25-6-to-791-7-billion-in-2025/; https://www.semiconductors.org/global-semiconductor-sales-increase-25-from-q4-2025-to-q1-2026/
A7: U.S. pre-seed market | B7: ~3,000 Carta startups / >$2.3B in Q1 2026 | C7: Expected final total around $2.9B | D7: Carta. Financing context only. | E7: https://carta.com/sg/en/data/state-of-pre-seed-q1-2026/
A8: U.S. seed valuation benchmark | B8: $18.4M median pre-money | C8: Q1 2026 | D8: PitchBook/NVCA. Not ATOMiK valuation. | E8: https://nvca.org/wp-content/uploads/2026/04/Q1-2026-PitchBook-NVCA-Venture-Monitor.pdf
A9: U.S. seed deal-size benchmark | B9: $3.0M median deal value | C9: Q1 2026 | D9: PitchBook/NVCA. Supports disciplined $2M ask. | E9: https://nvca.org/wp-content/uploads/2026/04/Q1-2026-PitchBook-NVCA-Venture-Monitor.pdf
A10: Accelerator comparables | B10: YC $500K; Techstars $220K | C10: Different program structures | D10: Dilution context; not direct round comps. | E10: https://www.ycombinator.com/deal; https://www.techstars.com/newsroom/investment-terms
A11: ASIC cost discipline | B11: NRE varies by design, node, IP, EDA, mask, packaging, test | C11: Use feasibility-first framing | D11: AnySilicon. Avoid false precision before expert quote. | E11: https://anysilicon.com/semiconductor-manufacturing-cost-breakdown/; https://anysilicon.com/asic-nre-explained/
A13: Market figures support why-now and financing context. They do not prove ATOMiK savings, customer demand, or valuation.

Sheet Cap Table Draft
A1: Cap Table - Draft Placeholder / Counsel Review Required
A3: Holder | B3: Security | C3: Shares | D3: Current Status | E3: Required Before Close
A4: Matthew Rockwell (Founder) | B4: Common | C4: TBD | D4: Founder / pre-close | E4: Incorporation, stock issuance, founder IP assignment.
A5: ESOP / Option Pool | B5: Common reserved | C5: TBD | D5: To be created | E5: CFO/counsel sizing; likely 10-15% discussion, not commitment.
A6: Pre-Seed Investors | B6: Planned SAFE | C6: N/A | D6: Planned | E6: Final SAFE terms, cap, discount, pro-rata, side letters.
A7: Prior instruments | B7: TBD | C7: TBD | D7: Must verify | E7: Confirm no hidden notes, grants, IP obligations, or advisor promises.
A10: Do not share this as a formal cap table. It is a diligence checklist until entity formation, stock issuance, and counsel-reviewed records are complete.

Sheet Unmodeled CFO Needs
A1: Unmodeled / CFO Estimate Needed
A2: These are visible diligence gaps, not hidden costs. Estimate with CFO/accounting/counsel before final model distribution.
A4: Item | B4: Why it matters | C4: Current treatment
A5: Payroll taxes | B5: Affects fully loaded burn. | C5: Not separately modeled; included only as broad finance/ops planning.
A6: Benefits | B6: Hiring costs differ materially by role and timing. | C6: Requires CFO/accounting estimate before hiring plan is shared.
A7: Insurance | B7: D&O, general liability, cyber, and hardware/customer evaluation coverage may be needed. | C7: Needs broker quote.
A8: Accounting/bookkeeping/tax | B8: Ongoing reporting and investor-readiness cost. | C8: Broadly included in Finance/GTM/Ops; estimate needed.
A9: Delaware C-Corp conversion | B9: Required for VC-ready close path if counsel chooses conversion/formation. | C9: Legal budget allocation exists; exact cost pending counsel.
A10: Legal close costs | B10: SAFE review, side letters, cap-table setup, and closing mechanics. | C10: Pending counsel/CFO.
A11: IP prosecution variability | B11: Patent conversion and prior-art work can vary. | C11: IP/legal allocation exists; quote needed.
A12: FPGA/dev-board/tooling | B12: Hardware validation may need boards, instruments, tools, and licenses. | C12: Demo/tooling allocation exists; vendor quotes needed.
A13: Cloud/dev infrastructure | B13: Build, storage, collaboration, and artifact hosting. | C13: Not separately forecast.
A14: Travel/customer evaluation support | B14: Design-partner work may require on-site support. | C14: Not separately forecast.
A15: Additional contingency | B15: Reserve may need adjustment after quotes. | C15: $150K reserve held; not CFO-approved contingency model.

Sheet Caveats
A1: Financial Diligence Caveats
A2: Topic | B2: Caveat
A3: No valuation recommendation | B3: The workbook shows dilution sensitivity only. It does not recommend a valuation cap.
A4: No revenue forecast | B4: Reservation-pricing scenarios are qualification signals, not forecast revenue or valuation support.
A5: No tape-out budget | B5: Pre-seed funds ASIC feasibility and quote-backed review, not production silicon.
A6: No customer traction claim | B6: Do not claim signed customers, LOIs, or revenue unless signed evidence exists.
A7: No outcome savings claim | B7: Battery, heat, cooling, water, footprint, and power-bill outcomes require workload-specific measurement.
A8: CFO/counsel review | B8: SAFE terms, cap, discount, pro-rata rights, option pool, tax/accounting treatment, and closing mechanics require review.
